jkinpylib/__init__.py
jkinpylib/config.py
jkinpylib/conversions.py
jkinpylib/evaluation.py
jkinpylib/robot.py
jkinpylib/robots.py
jkinpylib/urdf_utils.py
jkinpylib/utils.py
jkinpylib/urdfs/README.md
jkinpylib/urdfs/baxter/baxter.urdf
jkinpylib/urdfs/baxter/info.md
jkinpylib/urdfs/baxter/meshes/base/PEDESTAL.DAE
jkinpylib/urdfs/baxter/meshes/base/PEDESTAL.STL
jkinpylib/urdfs/baxter/meshes/base/pedestal_link_collision.DAE
jkinpylib/urdfs/baxter/meshes/base/pedestal_link_collision.STL
jkinpylib/urdfs/baxter/meshes/head/H0.DAE
jkinpylib/urdfs/baxter/meshes/head/H0.STL
jkinpylib/urdfs/baxter/meshes/head/H1.DAE
jkinpylib/urdfs/baxter/meshes/head/H1.STL
jkinpylib/urdfs/baxter/meshes/lower_elbow/E1.DAE
jkinpylib/urdfs/baxter/meshes/lower_elbow/E1.STL
jkinpylib/urdfs/baxter/meshes/lower_forearm/W1.DAE
jkinpylib/urdfs/baxter/meshes/lower_forearm/W1.STL
jkinpylib/urdfs/baxter/meshes/lower_shoulder/S1.DAE
jkinpylib/urdfs/baxter/meshes/lower_shoulder/S1.STL
jkinpylib/urdfs/baxter/meshes/torso/base_link.DAE
jkinpylib/urdfs/baxter/meshes/torso/base_link.STL
jkinpylib/urdfs/baxter/meshes/torso/base_link_collision.DAE
jkinpylib/urdfs/baxter/meshes/torso/base_link_collision.STL
jkinpylib/urdfs/baxter/meshes/upper_elbow/E0.DAE
jkinpylib/urdfs/baxter/meshes/upper_elbow/E0.STL
jkinpylib/urdfs/baxter/meshes/upper_forearm/W0.DAE
jkinpylib/urdfs/baxter/meshes/upper_forearm/W0.STL
jkinpylib/urdfs/baxter/meshes/upper_shoulder/S0.DAE
jkinpylib/urdfs/baxter/meshes/upper_shoulder/S0.STL
jkinpylib/urdfs/baxter/meshes/wrist/W2.DAE
jkinpylib/urdfs/baxter/meshes/wrist/W2.STL
jkinpylib/urdfs/fetch/README.md
jkinpylib/urdfs/fetch/fetch.pdf
jkinpylib/urdfs/fetch/fetch.urdf
jkinpylib/urdfs/fetch/fetch_formatted.urdf
jkinpylib/urdfs/fetch/meshes/base_link.dae
jkinpylib/urdfs/fetch/meshes/base_link_collision.STL
jkinpylib/urdfs/fetch/meshes/base_link_uv.png
jkinpylib/urdfs/fetch/meshes/bellows_link.STL
jkinpylib/urdfs/fetch/meshes/bellows_link_collision.STL
jkinpylib-0.0.9.dist-info/LICENSE.txt
jkinpylib-0.0.9.dist-info/METADATA
jkinpylib-0.0.9.dist-info/WHEEL
jkinpylib-0.0.9.dist-info/top_level.txt
jkinpylib-0.0.9.dist-info/RECORD
